tasky_cli/__init__.py
tasky_cli/__main__.py
tasky_cli/defaults.py
tasky_cli/tasky.py
tasky_cli-0.5.2.dist-info/licenses/LICENSE
tasky_cli-0.5.2.dist-info/METADATA
tasky_cli-0.5.2.dist-info/WHEEL
tasky_cli-0.5.2.dist-info/entry_points.txt
tasky_cli-0.5.2.dist-info/top_level.txt
tasky_cli-0.5.2.dist-info/RECORD
