Metadata-Version: 2.4
Name: tasky-cli
Version: 0.5.2
Summary: A to-do list CLI that's heavily inspired by klaudiosinani's taskbook (JavaScript).
Author-email: espehon <espehon@gmail.com>
Project-URL: Homepage, https://github.com/espehon/tasky-cli
Project-URL: Bug Tracker, https://github.com/espehon/tasky-cli/issues
Classifier: Programming Language :: Python :: 3
Classifier: Development Status :: 5 - Production/Stable
Classifier: Environment :: Console
Classifier: License :: OSI Approved :: MIT License
Classifier: Operating System :: OS Independent
Classifier: Topic :: Utilities
Requires-Python: >=3.10
License-File: LICENSE
Requires-Dist: colorama>=0.4.6
Requires-Dist: python-dateutil>=2.9.0
Requires-Dist: questionary>=2.1.0
Dynamic: license-file
